utils/__init__.py
utils/reload.py
watchghost/VERSION
watchghost/__init__.py
watchghost/__main__.py
watchghost/config.py
watchghost/json2toml.py
watchghost/loggers.py
watchghost/watchers.py
watchghost/web.py
watchghost/etc/groups
watchghost/etc/groups.toml
watchghost/etc/loggers
watchghost/etc/loggers.toml
watchghost/etc/servers
watchghost/etc/servers.toml
watchghost/etc/watchers
watchghost/etc/watchers.toml
watchghost/services/__init__.py
watchghost/services/command.py
watchghost/services/network.py
watchghost/services/whois.py
watchghost/static/axios.js
watchghost/static/bootstrap.css
watchghost/static/favicon.ico
watchghost/static/style.css
watchghost/static/vue-native-websocket.js
watchghost/static/vue-router.js
watchghost/static/vue.js
watchghost/static/watchghost.js
watchghost/templates/_layout.html
watchghost/templates/index.html
watchghost/templates/watcher.html
watchghost/tests/__init__.py
watchghost/tests/test_logger.py
watchghost/tests/test_should_log.py
watchghost/tests/test_watcher.py
watchghost-0.3.0.dist-info/LICENSE
watchghost-0.3.0.dist-info/METADATA
watchghost-0.3.0.dist-info/WHEEL
watchghost-0.3.0.dist-info/entry_points.txt
watchghost-0.3.0.dist-info/requirements.in
watchghost-0.3.0.dist-info/requirements.txt
watchghost-0.3.0.dist-info/top_level.txt
watchghost-0.3.0.dist-info/RECORD
